firesense/__init__.py
firesense/__main__.py
firesense/py.typed
firesense/demo-ui/index.html
firesense/demo-ui/assets/index-CaNFM47n.js
firesense/demo-ui/assets/index-Czz9Whz2.css
firesense/fire_detection/__init__.py
firesense/fire_detection/__main__.py
firesense/fire_detection/cli.py
firesense/fire_detection/config.py
firesense/fire_detection/demo_server.py
firesense/fire_detection/inference.py
firesense/fire_detection/mock_inference.py
firesense/fire_detection/mock_inference_pipeline.py
firesense/fire_detection/model.py
firesense/fire_detection/video.py
firesense-0.10.2.dist-info/METADATA
firesense-0.10.2.dist-info/WHEEL
firesense-0.10.2.dist-info/entry_points.txt
firesense-0.10.2.dist-info/licenses/LICENSE
firesense-0.10.2.dist-info/RECORD
